evcrew/__init__.py
evcrew/crew.py
evcrew/process.py
evcrew/utils.py
evcrew/agents/__init__.py
evcrew/agents/base.py
evcrew/agents/evaluator.py
evcrew/agents/improver.py
evcrew/agents/prompts/evaluator.md
evcrew/agents/prompts/improver.md
evcrew/agents/prompts/improver_task.md
evcrew/tests/__init__.py
evcrew/tests/test_agents.py
evcrew/tests/test_base_agent.py
evcrew/tests/test_crew.py
evcrew/tests/test_crew_methods.py
evcrew/tests/test_edge_cases.py
evcrew/tests/test_evaluator.py
evcrew/tests/test_process.py
evcrew/tests/test_save_methods.py
evcrew/tests/test_utils.py
autodoceval_crewai-0.4.4.dist-info/METADATA
autodoceval_crewai-0.4.4.dist-info/WHEEL
autodoceval_crewai-0.4.4.dist-info/licenses/LICENSE
autodoceval_crewai-0.4.4.dist-info/RECORD
